chocolate/__init__.py
chocolate/base.py
chocolate/conditional/__init__.py
chocolate/conditional/thompson.py
chocolate/connection/__init__.py
chocolate/connection/mongodb.py
chocolate/connection/pandas.py
chocolate/connection/postgresql.py
chocolate/connection/splitter.py
chocolate/connection/sqlite.py
chocolate/crossvalidation/__init__.py
chocolate/crossvalidation/repeat.py
chocolate/mo/__init__.py
chocolate/mo/_hv.c
chocolate/mo/_hv.h
chocolate/mo/hv.cpp
chocolate/mo/pyhv.py
chocolate/sample/__init__.py
chocolate/sample/grid.py
chocolate/sample/quasirandom.py
chocolate/sample/random.py
chocolate/search/__init__.py
chocolate/search/bayes.py
chocolate/search/cmaes.py
chocolate/search/kernels.py
chocolate/space.py
intelecy_chocolate-0.1.4.dist-info/LICENSE.txt
intelecy_chocolate-0.1.4.dist-info/WHEEL
intelecy_chocolate-0.1.4.dist-info/METADATA
intelecy_chocolate-0.1.4.dist-info/RECORD
